deepdriver/__init__.py
deepdriver/client_secrets.json
deepdriver/version.py
deepdriver/cli/cli.py
deepdriver/cli/cli_ctx.py
deepdriver/cli/cli_func.py
deepdriver/intergration/keras/keras.py
deepdriver/intergration/torch/torch.py
deepdriver/sdk/artifact.py
deepdriver/sdk/config.py
deepdriver/sdk/experiment.py
deepdriver/sdk/login.py
deepdriver/sdk/run.py
deepdriver/sdk/setting.py
deepdriver/sdk/util.py
deepdriver/sdk/visualization.py
deepdriver/sdk/watch.py
deepdriver/sdk/chart/bar.py
deepdriver/sdk/chart/chart.py
deepdriver/sdk/chart/confusion_matrix.py
deepdriver/sdk/chart/histogram.py
deepdriver/sdk/chart/line.py
deepdriver/sdk/chart/roc_curve.py
deepdriver/sdk/chart/scatter.py
deepdriver/sdk/data_types/artifactEntryInfo.py
deepdriver/sdk/data_types/artifactInfo.py
deepdriver/sdk/data_types/boundingBoxes.py
deepdriver/sdk/data_types/dataFrame.py
deepdriver/sdk/data_types/experiment.py
deepdriver/sdk/data_types/image.py
deepdriver/sdk/data_types/media.py
deepdriver/sdk/data_types/run.py
deepdriver/sdk/data_types/table.py
deepdriver/sdk/data_types/uploadInfo.py
deepdriver/sdk/interface/file_upload.py
deepdriver/sdk/interface/grpc_interface_pb2.py
deepdriver/sdk/interface/grpc_interface_pb2_grpc.py
deepdriver/sdk/interface/http_interface.py
deepdriver/sdk/interface/interface.py
deepdriver/sdk/lib/lazyloader.py
deepdriver/sdk/security/crypto.py
deepdriver-1.0.1.dist-info/LICENSE.txt
deepdriver-1.0.1.dist-info/METADATA
deepdriver-1.0.1.dist-info/WHEEL
deepdriver-1.0.1.dist-info/entry_points.txt
deepdriver-1.0.1.dist-info/top_level.txt
deepdriver-1.0.1.dist-info/RECORD
