Metadata-Version: 2.1
Name: deepdriver
Version: 1.0.1
Summary: deepdriver experiments
Home-page: https://bokchi.com
Author: bokchi
Author-email: molamola.bokchi@gmail.com
Project-URL: bokchi git hub, https://github.com/molabokchi
Classifier: Programming Language :: Python :: 3
Classifier: License :: OSI Approved :: MIT License
Classifier: Operating System :: OS Independent
Requires-Python: >=3.7
License-File: LICENSE.txt
Requires-Dist: wheel
Requires-Dist: assertpy
Requires-Dist: numpy
Requires-Dist: pandas
Requires-Dist: Pillow
Requires-Dist: plotly
Requires-Dist: psutil
Requires-Dist: pynvml
Requires-Dist: requests
Requires-Dist: optuna
Requires-Dist: psycopg2
Requires-Dist: click
Requires-Dist: pycryptodome
Requires-Dist: google-auth-oauthlib
Requires-Dist: ipywidgets
